MANIFEST.in
setup.py
lighttable/__init__.py
lighttable/lightpivot.cpython-36m-x86_64-linux-gnu.so
lighttable.egg-info/PKG-INFO
lighttable.egg-info/SOURCES.txt
lighttable.egg-info/dependency_links.txt
lighttable.egg-info/not-zip-safe
lighttable.egg-info/top_level.txt