Metadata-Version: 1.0
Name: lighttable
Version: 0.3.2
Summary: light pivot feature engineer
Home-page: http://github.com/fe/lightpivot2
Author: fefly
Author-email: fefly@gmail.com
License: MIT
Platform: UNKNOWN
